{
  "count": 271,
  "uniques": 93,
  "views": [
    {
      "timestamp": "2023-09-27T00:00:00Z",
      "count": 16,
      "uniques": 8
    },
    {
      "timestamp": "2023-09-28T00:00:00Z",
      "count": 24,
      "uniques": 12
    },
    {
      "timestamp": "2023-09-29T00:00:00Z",
      "count": 18,
      "uniques": 9
    },
    {
      "timestamp": "2023-09-30T00:00:00Z",
      "count": 37,
      "uniques": 13
    },
    {
      "timestamp": "2023-10-01T00:00:00Z",
      "count": 46,
      "uniques": 17
    },
    {
      "timestamp": "2023-10-02T00:00:00Z",
      "count": 104,
      "uniques": 20
    },
    {
      "timestamp": "2023-10-03T00:00:00Z",
      "count": 26,
      "uniques": 14
    }
  ]
}